README.md
setup.py
fvid/__init__.py
fvid/__main__.py
fvid/cythonizer.py
fvid/fvid.py
fvid/fvid_cython.c
fvid.egg-info/PKG-INFO
fvid.egg-info/SOURCES.txt
fvid.egg-info/dependency_links.txt
fvid.egg-info/entry_points.txt
fvid.egg-info/not-zip-safe
fvid.egg-info/requires.txt
fvid.egg-info/top_level.txt