Metadata-Version: 2.1
Name: fvid
Version: 1.0.0
Summary: fvid is a project that aims to encode any file as a video using 1-bit color images to survive compression algorithms for data retrieval.
Home-page: https://github.com/AlfredoSequeida/fvid
Author: Alfredo Sequeida
License: MIT
Download-URL: https://github.com/AlfredoSequeida/fvid/archive/1.0.0.tar.gz
Keywords: fvid youtube videos files bitdum hexdump ffmpeg video file
Platform: any
Classifier: Intended Audience :: End Users/Desktop
Classifier: License :: OSI Approved :: MIT License
Classifier: Programming Language :: Python :: 3
Classifier: Programming Language :: Python :: 3.6
Classifier: Programming Language :: Python :: 3.7
Classifier: Programming Language :: Python :: 3.8
Classifier: Programming Language :: Python :: 3.9
Classifier: Operating System :: Microsoft :: Windows :: Windows 10
Classifier: Operating System :: Microsoft :: Windows :: Windows 8
Classifier: Operating System :: Microsoft :: Windows :: Windows 8.1
Classifier: Operating System :: MacOS :: MacOS X
Classifier: Operating System :: POSIX :: Linux
Requires-Python: >=3.6
